octoface/__init__.py
octoface/cli.py
octoface/downloader.py
octoface/github.py
octoface/uploader.py
octoface/utils.py
octoface-0.3.0.dist-info/METADATA
octoface-0.3.0.dist-info/WHEEL
octoface-0.3.0.dist-info/entry_points.txt
octoface-0.3.0.dist-info/top_level.txt
octoface-0.3.0.dist-info/RECORD
