Metadata-Version: 2.4
Name: octoface
Version: 0.3.0
Summary: CLI tool for managing LLM models on IPFS and GitHub Pages
Author-email: OctoFaceHub Team <info@octofacehub.org>
License: MIT
Project-URL: Homepage, https://github.com/octofacehub/octoface
Project-URL: Bug Tracker, https://github.com/octofacehub/octoface/issues
Classifier: Programming Language :: Python :: 3
Classifier: License :: OSI Approved :: MIT License
Classifier: Operating System :: OS Independent
Requires-Python: >=3.7
Requires-Dist: click>=8.0.0
Requires-Dist: requests>=2.25.0
Requires-Dist: huggingface-hub>=0.10.0
Requires-Dist: rich>=12.0.0
